stambo/__init__.py
stambo/_predsamplewrapper.py
stambo/_stambo.py
stambo/_utils.py
stambo/metrics.py
stambo/synthetic.py
stambo-0.1.5.dist-info/licenses/LICENSE
stambo-0.1.5.dist-info/METADATA
stambo-0.1.5.dist-info/WHEEL
stambo-0.1.5.dist-info/top_level.txt
stambo-0.1.5.dist-info/RECORD
