Metadata-Version: 2.4
Name: stambo
Version: 0.1.5
Summary: A library for statistical model comparison using bootstrap.
Author-email: Aleksei Tiulpin <aleksei.tiulpin@gmail.com>
License: MIT
Project-URL: Homepage, https://github.com/imedslab/stambo
Keywords: statistical testing,machine learning
Classifier: Development Status :: 5 - Production/Stable
Classifier: Intended Audience :: Science/Research
Classifier: License :: OSI Approved :: MIT License
Classifier: Natural Language :: English
Classifier: Programming Language :: Python :: 3.8
Classifier: Programming Language :: Python :: 3.9
Classifier: Programming Language :: Python :: 3.10
Classifier: Programming Language :: Python :: 3.11
Classifier: Programming Language :: Python :: 3.12
Classifier: Operating System :: MacOS
Classifier: Operating System :: POSIX :: Linux
Requires-Python: >=3.9
License-File: LICENSE
Requires-Dist: numpy>=2.0.0
Requires-Dist: scikit-learn>=1.3.0
Requires-Dist: tqdm>=4.0.0
Requires-Dist: matplotlib>=3.9.4
Requires-Dist: ipywidgets>=8.1.8
Provides-Extra: test
Requires-Dist: pytest; extra == "test"
Requires-Dist: pytest-cov; extra == "test"
Provides-Extra: dev
Requires-Dist: pytest; extra == "dev"
Requires-Dist: pytest-cov; extra == "dev"
Requires-Dist: ipython; extra == "dev"
Requires-Dist: ipykernel; extra == "dev"
Requires-Dist: sphinx; extra == "dev"
Requires-Dist: nbsphinx; extra == "dev"
Requires-Dist: nbsphinx-link; extra == "dev"
Requires-Dist: sphinx-rtd-theme; extra == "dev"
Requires-Dist: furo; extra == "dev"
Requires-Dist: typing_extensions; extra == "dev"
Requires-Dist: pandoc; extra == "dev"
Dynamic: license-file
